sandcastle/__init__.py
sandcastle/api.py
sandcastle/exceptions.py
sandcastle/kube.py
sandcastle/utils.py
sandcastle-0.1.0.dist-info/LICENSE
sandcastle-0.1.0.dist-info/METADATA
sandcastle-0.1.0.dist-info/WHEEL
sandcastle-0.1.0.dist-info/top_level.txt
sandcastle-0.1.0.dist-info/RECORD
