Metadata-Version: 2.1
Name: sandcastle
Version: 0.1.0
Summary: Run untrusted commands in a sandbox.
Home-page: https://github.com/packit-service/sandcastle
Author: Red Hat
Author-email: user-cont-team@redhat.com
License: MIT
Keywords: openshift,sandbox
Platform: UNKNOWN
Classifier: Intended Audience :: Developers
Classifier: License :: OSI Approved :: MIT License
Classifier: Operating System :: POSIX :: Linux
Classifier: Programming Language :: Python
Classifier: Programming Language :: Python :: 3.6
Classifier: Programming Language :: Python :: 3.7
Classifier: Topic :: Software Development
Classifier: Topic :: Utilities
Requires-Python: >=3.6
Requires-Dist: kubernetes (<9)
